web_poe_api/__init__.py
web_poe_api-1.0.0.dist-info/LICENSE.txt
web_poe_api-1.0.0.dist-info/METADATA
web_poe_api-1.0.0.dist-info/WHEEL
web_poe_api-1.0.0.dist-info/top_level.txt
web_poe_api-1.0.0.dist-info/RECORD
