Metadata-Version: 2.1
Name: web-poe-api
Version: 1.0.0
Summary: some useful api from poe.com
Home-page: https://github.com/canxin121/web_poe_api
Author: canxin
Author-email: 1969730106@qq.com
Classifier: Programming Language :: Python :: 3
Classifier: License :: OSI Approved :: MIT License
Classifier: Operating System :: OS Independent
Requires-Python: >=3.6
License-File: LICENSE.txt
